config/__init__.py
config/settings.py
docs/__init__.py
lambda_deploy/__init__.py
lambda_deploy/api_gateway_manager.py
lambda_deploy/api_gateway_stack.py
lambda_deploy/app.py
lambda_deploy/app_stack.py
lambda_deploy/decorators.py
lambda_deploy/deployment.py
lambda_deploy/docker_manager.py
lambda_deploy/handler_stack.py
lambda_deploy/lambda_deploy_stack.py
lambda_deploy/lambda_manager.py
lambda_deploy/layer_manager.py
lambda_deploy/pydantic_models.py
lambda_deploy/s3_manager.py
tests/__init__.py
tests/integration/__init__.py
tests/mock_integration/__init__.py
tests/mock_integration/test_api_gateway_manager_mock_integration.py
tests/mock_integration/test_lambda_manager_mock_integration.py
tests/mock_integration/test_layer_manager_mock_integration.py
tests/mock_integration/test_s3_manager_mock_integration.py
tests/unit/__init__.py
lambda_deploy_krhobeck-0.1.60.dist-info/LICENSE
lambda_deploy_krhobeck-0.1.60.dist-info/METADATA
lambda_deploy_krhobeck-0.1.60.dist-info/WHEEL
lambda_deploy_krhobeck-0.1.60.dist-info/entry_points.txt
lambda_deploy_krhobeck-0.1.60.dist-info/top_level.txt
lambda_deploy_krhobeck-0.1.60.dist-info/RECORD
